[{"type":"constructor","inputs":[{"name":"_proofVerifier","type":"address","internalType":"address"},{"name":"_aggregationVkey","type":"bytes32","internalType":"bytes32"},{"name":"_asr","type":"address","internalType":"contract IComposeAnchorStateRegistry"},{"name":"_authorizedProposer","type":"address","internalType":"address"}],"stateMutability":"nonpayable"},{"type":"function","name":"AGGREGATION_VKEY","inputs":[],"outputs":[{"name":"","type":"bytes32","internalType":"bytes32"}],"stateMutability":"view"},{"type":"function","name":"ANCHOR_STATE_REGISTRY","inputs":[],"outputs":[{"name":"","type":"address","internalType":"contract IComposeAnchorStateRegistry"}],"stateMutability":"view"},{"type":"function","name":"AUTHORIZED_PROPOSER","inputs":[],"outputs":[{"name":"","type":"address","internalType":"address"}],"stateMutability":"view"},{"type":"function","name":"COMPOSE_GAME_TYPE","inputs":[],"outputs":[{"name":"","type":"uint32","internalType":"uint32"}],"stateMutability":"view"},{"type":"function","name":"PROOF_VERIFIER","inputs":[],"outputs":[{"name":"","type":"address","internalType":"contract ISP1Verifier"}],"stateMutability":"view"},{"type":"function","name":"anchorStateRegistry","inputs":[],"outputs":[{"name":"registry_","type":"address","internalType":"contract IComposeAnchorStateRegistry"}],"stateMutability":"view"},{"type":"function","name":"closeGame","inputs":[],"outputs":[],"stateMutability":"nonpayable"},{"type":"function","name":"createdAt","inputs":[],"outputs":[{"name":"","type":"uint64","internalType":"Timestamp"}],"stateMutability":"view"},{"type":"function","name":"extraData","inputs":[],"outputs":[{"name":"extraData_","type":"bytes","internalType":"bytes"}],"stateMutability":"pure"},{"type":"function","name":"gameCreator","inputs":[],"outputs":[{"name":"","type":"address","internalType":"address"}],"stateMutability":"pure"},{"type":"function","name":"gameData","inputs":[],"outputs":[{"name":"gameType_","type":"uint32","internalType":"GameType"},{"name":"rootClaim_","type":"bytes32","internalType":"Claim"},{"name":"extraData_","type":"bytes","internalType":"bytes"}],"stateMutability":"pure"},{"type":"function","name":"gameType","inputs":[],"outputs":[{"name":"","type":"uint32","internalType":"GameType"}],"stateMutability":"pure"},{"type":"function","name":"initialize","inputs":[],"outputs":[],"stateMutability":"payable"},{"type":"function","name":"l1Head","inputs":[],"outputs":[{"name":"","type":"bytes32","internalType":"Hash"}],"stateMutability":"pure"},{"type":"function","name":"l2BlockNumber","inputs":[],"outputs":[{"name":"l2BlockNumber_","type":"uint256","internalType":"uint256"}],"stateMutability":"pure"},{"type":"function","name":"l2SequenceNumber","inputs":[],"outputs":[{"name":"l2SequenceNumber_","type":"uint256","internalType":"uint256"}],"stateMutability":"pure"},{"type":"function","name":"lastSuperblockNumber","inputs":[],"outputs":[{"name":"","type":"uint256","internalType":"uint256"}],"stateMutability":"view"},{"type":"function","name":"latestOutputsByConfig","inputs":[{"name":"","type":"bytes32","internalType":"bytes32"}],"outputs":[{"name":"l1Head","type":"bytes32","internalType":"bytes32"},{"name":"outputRoot","type":"bytes32","internalType":"bytes32"},{"name":"l2BlockNumber","type":"uint64","internalType":"uint64"}],"stateMutability":"view"},{"type":"function","name":"resolve","inputs":[],"outputs":[{"name":"status_","type":"uint8","internalType":"enum GameStatus"}],"stateMutability":"nonpayable"},{"type":"function","name":"resolvedAt","inputs":[],"outputs":[{"name":"","type":"uint64","internalType":"Timestamp"}],"stateMutability":"view"},{"type":"function","name":"rootClaim","inputs":[],"outputs":[{"name":"","type":"bytes32","internalType":"Claim"}],"stateMutability":"pure"},{"type":"function","name":"status","inputs":[],"outputs":[{"name":"","type":"uint8","internalType":"enum GameStatus"}],"stateMutability":"view"},{"type":"function","name":"version","inputs":[],"outputs":[{"name":"","type":"string","internalType":"string"}],"stateMutability":"view"},{"type":"function","name":"wasRespectedGameTypeWhenCreated","inputs":[],"outputs":[{"name":"","type":"bool","internalType":"bool"}],"stateMutability":"view"},{"type":"event","name":"GameClosed","inputs":[],"anonymous":false},{"type":"event","name":"L2OutputProposed","inputs":[{"name":"superblockNumber","type":"uint256","indexed":true,"internalType":"uint256"},{"name":"chainId","type":"uint256","indexed":true,"internalType":"uint256"},{"name":"l2BlockNumber","type":"uint256","indexed":true,"internalType":"uint256"},{"name":"rollupConfigHash","type":"bytes32","indexed":false,"internalType":"bytes32"},{"name":"outputRoot","type":"bytes32","indexed":false,"internalType":"bytes32"},{"name":"l1Head","type":"bytes32","indexed":false,"internalType":"bytes32"},{"name":"l1Timestamp","type":"uint256","indexed":false,"internalType":"uint256"}],"anonymous":false},{"type":"event","name":"Resolved","inputs":[{"name":"status","type":"uint8","indexed":true,"internalType":"enum GameStatus"}],"anonymous":false},{"type":"event","name":"SuperblockProposed","inputs":[{"name":"superblockNumber","type":"uint256","indexed":true,"internalType":"uint256"},{"name":"parentSuperblockBatchHash","type":"bytes32","indexed":false,"internalType":"bytes32"},{"name":"superblockTimestamp","type":"uint64","indexed":false,"internalType":"uint64"},{"name":"l1BlockNumber","type":"uint256","indexed":false,"internalType":"uint256"},{"name":"superRootClaim","type":"bytes32","indexed":false,"internalType":"bytes32"}],"anonymous":false},{"type":"error","name":"AlreadyInitialized","inputs":[]},{"type":"error","name":"EmptyOutputRoot","inputs":[]},{"type":"error","name":"Encoding_EmptySuperRoot","inputs":[]},{"type":"error","name":"Encoding_InvalidSuperRootVersion","inputs":[]},{"type":"error","name":"FutureTimestampProposed","inputs":[{"name":"submitted","type":"uint64","internalType":"uint64"},{"name":"current","type":"uint64","internalType":"uint64"}]},{"type":"error","name":"GameNotFinalized","inputs":[]},{"type":"error","name":"GameNotInProgress","inputs":[]},{"type":"error","name":"GamePaused","inputs":[]},{"type":"error","name":"InvalidASR","inputs":[]},{"type":"error","name":"InvalidRootClaim","inputs":[{"name":"expected","type":"bytes32","internalType":"bytes32"},{"name":"provided","type":"bytes32","internalType":"bytes32"}]},{"type":"error","name":"InvalidSuperblockOrdering","inputs":[{"name":"previous","type":"uint256","internalType":"uint256"},{"name":"current","type":"uint256","internalType":"uint256"}]},{"type":"error","name":"InvalidVerifier","inputs":[]},{"type":"error","name":"MissingAggregationProof","inputs":[]},{"type":"error","name":"OutputLengthMismatch","inputs":[{"name":"bootLength","type":"uint256","internalType":"uint256"},{"name":"rootLength","type":"uint256","internalType":"uint256"}]},{"type":"error","name":"OutputRootMismatch","inputs":[{"name":"chainId","type":"uint256","internalType":"uint256"},{"name":"expected","type":"bytes32","internalType":"bytes32"},{"name":"actual","type":"bytes32","internalType":"bytes32"}]},{"type":"error","name":"UnauthorizedProposer","inputs":[]}]